CHANGES.txt
COPYRIGHT.txt
LICENSE.txt
bootstrap.py
buildout.cfg
setup.py
src/sw/__init__.py
src/sw.objectinspection.egg-info/PKG-INFO
src/sw.objectinspection.egg-info/SOURCES.txt
src/sw.objectinspection.egg-info/dependency_links.txt
src/sw.objectinspection.egg-info/namespace_packages.txt
src/sw.objectinspection.egg-info/not-zip-safe
src/sw.objectinspection.egg-info/requires.txt
src/sw.objectinspection.egg-info/top_level.txt
src/sw/objectinspection/README.txt
src/sw/objectinspection/__init__.py
src/sw/objectinspection/configure.zcml
src/sw/objectinspection/ftesting.zcml
src/sw/objectinspection/testing.py
src/sw/objectinspection/tests.py