Metadata-Version: 1.0
Name: sw.objectinspection
Version: 1.0.1
Summary: Provides an API to access an objects references (children).
Home-page: UNKNOWN
Author: Sebastian Wehrmann
Author-email: sw@gocept.com
License: ZPL 2.1
Platform: UNKNOWN
Classifier: Intended Audience :: Developers
Classifier: License :: OSI Approved :: Zope Public License
Classifier: Programming Language :: Python
Classifier: Natural Language :: English
Classifier: Operating System :: OS Independent
Classifier: Topic :: Database
